{
  "items": [
    {
      "id": "t001",
      "text": "报销梳理xxxx",
      "tab": "today",
      "quadrant": "important-not-urgent",
      "completed": false,
      "completed_at": null,
      "created_at": "2025-01-01T09:00:00",
      "updated_at": "2025-12-27T09:43:09.981477"
    },
    {
      "id": "t002",
      "text": "所长上岗大纲梳理",
      "tab": "today",
      "quadrant": "important-urgent",
      "completed": false,
      "completed_at": null,
      "created_at": "2025-01-01T09:00:00",
      "updated_at": "2025-12-27T09:48:48.095369"
    },
    {
      "id": "t003",
      "text": "教授谈话问题总结",
      "tab": "today",
      "quadrant": "important-urgent",
      "completed": false,
      "completed_at": null,
      "created_at": "2025-01-01T09:00:00",
      "updated_at": "2025-12-27T09:39:05.115261"
    },
    {
      "id": "t004",
      "text": "zhiwei情况梳理，总结",
      "tab": "today",
      "quadrant": "important-not-urgent",
      "completed": false,
      "completed_at": null,
      "created_at": "2025-01-01T09:00:00",
      "updated_at": "2025-12-27T09:38:59.983382"
    },
    {
      "id": "t005",
      "text": "wei ou情况梳理总结",
      "tab": "today",
      "quadrant": "important-urgent",
      "completed": false,
      "completed_at": null,
      "created_at": "2025-01-01T09:00:00",
      "updated_at": "2025-12-27T09:25:25.922343"
    },
    {
      "id": "w001",
      "text": "学校申请进度跟踪",
      "tab": "month",
      "quadrant": "important-not-urgent",
      "completed": false,
      "completed_at": null,
      "created_at": "2025-01-01T09:00:00",
      "updated_at": "2025-12-27T10:01:06.853841"
    },
    {
      "id": "w002",
      "text": "报销",
      "tab": "today",
      "quadrant": "important-not-urgent",
      "completed": false,
      "completed_at": null,
      "created_at": "2025-01-01T09:00:00",
      "updated_at": "2025-12-27T10:01:26.247943"
    },
    {
      "id": "w003",
      "text": "补助申请，跟进房补、餐补等",
      "tab": "week",
      "quadrant": "important-urgent",
      "completed": false,
      "completed_at": null,
      "created_at": "2025-01-01T09:00:00",
      "updated_at": "2025-12-27T09:27:28.142574"
    },
    {
      "id": "w004",
      "text": "2.3~2.6年度会议差旅计划",
      "tab": "week",
      "quadrant": "important-not-urgent",
      "completed": false,
      "completed_at": null,
      "created_at": "2025-01-01T09:00:00",
      "updated_at": "2025-01-01T09:00:00"
    },
    {
      "id": "w005",
      "text": "邱所工作交接，制定初步后续工作计划",
      "tab": "week",
      "quadrant": "important-urgent",
      "completed": false,
      "completed_at": null,
      "created_at": "2025-01-01T09:00:00",
      "updated_at": "2025-01-01T09:00:00"
    },
    {
      "id": "w006",
      "text": "90天转身计划",
      "tab": "week",
      "quadrant": "important-not-urgent",
      "completed": false,
      "completed_at": null,
      "created_at": "2025-01-01T09:00:00",
      "updated_at": "2025-01-01T09:00:00"
    },
    {
      "id": "w007",
      "text": "光的case，蓝军实验室计划",
      "tab": "week",
      "quadrant": "important-not-urgent",
      "completed": false,
      "completed_at": null,
      "created_at": "2025-01-01T09:00:00",
      "updated_at": "2025-12-27T09:43:42.311210"
    },
    {
      "id": "w008",
      "text": "严华兵合作，进展交流",
      "tab": "week",
      "quadrant": "important-not-urgent",
      "completed": false,
      "completed_at": null,
      "created_at": "2025-01-01T09:00:00",
      "updated_at": "2025-12-27T10:00:56.599089"
    },
    {
      "id": "w009",
      "text": "亮哥培训",
      "tab": "week",
      "quadrant": "important-urgent",
      "completed": false,
      "completed_at": null,
      "created_at": "2025-01-01T09:00:00",
      "updated_at": "2025-12-27T09:43:49.029367"
    },
    {
      "id": "w010",
      "text": "工作交接list梳理",
      "tab": "week",
      "quadrant": "important-not-urgent",
      "completed": false,
      "completed_at": null,
      "created_at": "2025-01-01T09:00:00",
      "updated_at": "2025-01-01T09:00:00"
    },
    {
      "id": "w011",
      "text": "几个talk准备（健身、颁奖、自我介绍）",
      "tab": "week",
      "quadrant": "important-urgent",
      "completed": false,
      "completed_at": null,
      "created_at": "2025-01-01T09:00:00",
      "updated_at": "2025-12-27T09:27:39.712910"
    },
    {
      "id": "m001",
      "text": "任职计划",
      "tab": "month",
      "quadrant": "important-not-urgent",
      "completed": false,
      "completed_at": null,
      "created_at": "2025-01-01T09:00:00",
      "updated_at": "2025-01-01T09:00:00"
    },
    {
      "id": "m002",
      "text": "2.3~2.6年度会议",
      "tab": "month",
      "quadrant": "important-urgent",
      "completed": false,
      "completed_at": null,
      "created_at": "2025-01-01T09:00:00",
      "updated_at": "2025-01-01T09:00:00"
    },
    {
      "id": "m003",
      "text": "驾照",
      "tab": "month",
      "quadrant": "not-important-not-urgent",
      "completed": false,
      "completed_at": null,
      "created_at": "2025-01-01T09:00:00",
      "updated_at": "2025-01-01T09:00:00"
    },
    {
      "id": "m004",
      "text": "小闭环想法",
      "tab": "month",
      "quadrant": "important-not-urgent",
      "completed": false,
      "completed_at": null,
      "created_at": "2025-01-01T09:00:00",
      "updated_at": "2025-01-01T09:00:00"
    },
    {
      "id": "m005",
      "text": "上岗谈话",
      "tab": "month",
      "quadrant": "important-urgent",
      "completed": false,
      "completed_at": null,
      "created_at": "2025-01-01T09:00:00",
      "updated_at": "2025-01-01T09:00:00"
    },
    {
      "id": "m006",
      "text": "上岗talk（英文）",
      "tab": "month",
      "quadrant": "important-urgent",
      "completed": false,
      "completed_at": null,
      "created_at": "2025-01-01T09:00:00",
      "updated_at": "2025-12-27T10:01:16.159771"
    },
    {
      "id": "m007",
      "text": "公司调研：企业、AI4coding",
      "tab": "month",
      "quadrant": "important-not-urgent",
      "completed": false,
      "completed_at": null,
      "created_at": "2025-01-01T09:00:00",
      "updated_at": "2025-01-01T09:00:00"
    },
    {
      "id": "7722c591",
      "text": "ssssss",
      "tab": "week",
      "quadrant": "not-important-not-urgent",
      "completed": false,
      "completed_at": null,
      "created_at": "2025-12-27T08:00:30.761924",
      "updated_at": "2025-12-27T09:54:28.511476"
    },
    {
      "id": "e92ac481",
      "text": "sdfsdf",
      "tab": "today",
      "quadrant": "not-important-urgent",
      "completed": false,
      "completed_at": null,
      "created_at": "2025-12-27T09:22:43.219408",
      "updated_at": "2025-12-27T09:39:15.310918"
    }
  ]
}